Metadata-Version: 2.1
Name: maga5416calculator
Version: 0.1
Summary: Simple math calculator
Author: Marta Garsvaite
